statml/__init__.py
statml/playchat.py
statml/stepwise.py
statml/data/four/1-4-6-data.csv
statml/data/four/1-통계학 기본.ipynb
statml/data/four/2-02-Jupyter Notebook.ipynb
statml/data/four/2-03. 파이썬 프로그래밍 기본.ipynb
statml/data/four/2-04. numpy와 pandas 기본.ipynb
statml/data/four/2-4-1-sample_data.csv
statml/data/four/3-01. 파이썬을 이용한 기술통계_1변량데이터.ipynb
statml/data/four/3-02. 파이썬을 이용한 기술통계_다변량데이터.ipynb
statml/data/four/3-03. matplotlib과 seaborn을 이용한 데이터 시각화.ipynb
statml/data/four/3-04. 모집단에서 표본 추출 시뮬레이션.ipynb
statml/data/four/3-05. 표본 통계량 성질.ipynb
statml/data/four/3-06. 정규분포와 응용.ipynb
statml/data/four/3-07. 추정.ipynb
statml/data/four/3-08. 통계적가설검정.ipynb
statml/data/four/3-09. 평균값의 차이 검정.ipynb
statml/data/four/3-10-1-click_data.csv
statml/data/four/3-10. 분할표 검정.ipynb
statml/data/four/3-2-1-fish_multi.csv
statml/data/four/3-2-2-shoes.csv
statml/data/four/3-2-3-cov.csv
statml/data/four/3-3-2-fish_multi_2.csv
statml/data/four/3-4-1-fish_length_100000.csv
statml/data/four/3-7-1-fish_length.csv
statml/data/four/3-8-1-junk-food-weight.csv
statml/data/four/3-9-1-paired-t-test.csv
statml/data/four/5-01.연속형 독립변수가 하나인 모델(단순회귀).ipynb
statml/data/four/5-02.분산분석.ipynb
statml/data/four/5-03. 독립변수가 여럿인 모델.ipynb
statml/data/four/5-1-1-beer.csv
statml/data/four/5-3-1-lm-model.csv
statml/data/four/6-01.여러가지 확률분포.ipynb
statml/data/four/6-03. 로지스틱 회귀.ipynb
statml/data/four/6-04.일반선형모델의 평가.ipynb
statml/data/four/6-05.푸아송 회귀.ipynb
statml/data/four/6-3-1-logistic-regression.csv
statml/data/four/6-5-1-poisson-regression.csv
statml/data/four/7-03. 파이썬을 이용한 리지 회귀와 라소 회귀.ipynb
statml/data/four/7-04.선형모델과 신경망.ipynb
statml/data/four/7-3-1-large-data.csv
statml/data/four/README.md
statml/data/one/2_datahandling/Ch2-10.ipynb
statml/data/one/2_datahandling/Ch2-11.ipynb
statml/data/one/2_datahandling/Ch2-2.ipynb
statml/data/one/2_datahandling/Ch2-3.ipynb
statml/data/one/2_datahandling/Ch2-4.ipynb
statml/data/one/2_datahandling/Ch2-5.ipynb
statml/data/one/2_datahandling/Ch2-6.ipynb
statml-0.0.10.dist-info/LICENSE
statml-0.0.10.dist-info/METADATA
statml-0.0.10.dist-info/WHEEL
statml-0.0.10.dist-info/top_level.txt
statml-0.0.10.dist-info/RECORD
